gunicorn_uvicorn_runner/__init__.py
gunicorn_uvicorn_runner/core.py
gunicorn_uvicorn_runner-0.1.3.dist-info/LICENSE
gunicorn_uvicorn_runner-0.1.3.dist-info/METADATA
gunicorn_uvicorn_runner-0.1.3.dist-info/WHEEL
gunicorn_uvicorn_runner-0.1.3.dist-info/RECORD
