Metadata-Version: 2.1
Name: gunicorn-uvicorn-runner
Version: 0.1.3
Summary: Run either gunicorn or uvicorn depending on whether reloading is needed.
Home-page: https://github.com/Jaza/gunicorn-uvicorn-runner
License: Apache-2.0
Author: Jeremy Epstein
Author-email: jazepstein@gmail.com
Requires-Python: >=3.10,<4
Classifier: License :: OSI Approved :: Apache Software License
Classifier: Programming Language :: Python :: 3
Classifier: Programming Language :: Python :: 3.10
Classifier: Programming Language :: Python :: 3.11
Requires-Dist: gunicorn
Requires-Dist: uvicorn[standard]
